CHANGELOG.md
MANIFEST.in
README.md
_upload.txt
requirements.txt
setup.py
unin/__init__.py
unin.egg-info/PKG-INFO
unin.egg-info/SOURCES.txt
unin.egg-info/dependency_links.txt
unin.egg-info/requires.txt
unin.egg-info/top_level.txt
unin/misc/__init__.py
unin/misc/_meta.py